click_template_cli/__init__.py
click_template_cli/cli.py
tests/__init__.py
tests/test_cli.py
click_app-0.1.5.dist-info/LICENSE
click_app-0.1.5.dist-info/METADATA
click_app-0.1.5.dist-info/WHEEL
click_app-0.1.5.dist-info/entry_points.txt
click_app-0.1.5.dist-info/top_level.txt
click_app-0.1.5.dist-info/RECORD
