Metadata-Version: 2.1
Name: click_app
Version: 0.1.5
Summary: A template of Click application CLI
Home-page: https://github.com/chuangtc/click-template-cli
Author: Jason Chuang
Author-email: chuangtcee@gmail.com
Classifier: Programming Language :: Python :: 3
Classifier: License :: OSI Approved :: MIT License
Classifier: Operating System :: OS Independent
Requires-Python: >=3.8
License-File: LICENSE
Requires-Dist: click >=8.0.0
